odoolint/__init__.py
odoolint/config.py
odoolint/file_checker.py
odoolint/main.py
odoolint/module_finder.py
odoolint/python_checker.py
odoolint/xml_checker.py
odoolint-1.9.dist-info/METADATA
odoolint-1.9.dist-info/WHEEL
odoolint-1.9.dist-info/entry_points.txt
odoolint-1.9.dist-info/top_level.txt
odoolint-1.9.dist-info/RECORD
