Metadata-Version: 2.1
Name: odoolint
Version: 1.9
Summary: A comprehensive linting tool for Odoo modules
Home-page: https://github.com/dgperp/odoolint
Author: Your Name
Author-email: your.email@example.com
License: UNKNOWN
Project-URL: Bug Reports, https://github.com/dgperp/odoolint/issues
Project-URL: Source, https://github.com/dgperp/odoolint/
Keywords: odoo,linter,development,tools
Platform: UNKNOWN
Classifier: Development Status :: 3 - Alpha
Classifier: Intended Audience :: Developers
Classifier: Topic :: Software Development :: Quality Assurance
Classifier: License :: OSI Approved :: MIT License
Classifier: Programming Language :: Python :: 3
Classifier: Programming Language :: Python :: 3.6
Classifier: Programming Language :: Python :: 3.7
Classifier: Programming Language :: Python :: 3.8
Classifier: Programming Language :: Python :: 3.9
Requires-Python: >=3.6, <4
Requires-Dist: flake8
Requires-Dist: pyyaml
